smoldyn/__init__.py
smoldyn/__main__.py
smoldyn/_smoldyn.cp37-win_amd64.pyd
smoldyn/smoldyn.py
smoldyn/types.py
smoldyn/utils.py
smoldyn/biosimulators/__init__.py
smoldyn/biosimulators/__main__.py
smoldyn/biosimulators/_version.py
smoldyn/biosimulators/combine.py
smoldyn/biosimulators/data_model.py
smoldyn/biosimulators/tests.py
smoldyn/biosimulators/utils.py
smoldyn-2.75.dist-info/METADATA
smoldyn-2.75.dist-info/WHEEL
smoldyn-2.75.dist-info/top_level.txt
smoldyn-2.75.dist-info/RECORD
