Metadata-Version: 2.1
Name: smoldyn
Version: 2.75
Summary: Python package for the Smoldyn simulator
Home-page: http://www.smoldyn.org/
Author: Dilawar Singh
Author-email: dilawar.s.rajput@gmail.com
License: GNU LGPLv3
Platform: UNKNOWN
Classifier: Development Status :: 3 - Alpha
Classifier: Intended Audience :: Science/Research
Classifier: License :: OSI Approved :: GNU Lesser General Public License v3 (LGPLv3)
Classifier: Natural Language :: English
Classifier: Operating System :: OS Independent
Classifier: Programming Language :: Python :: 3 :: Only
Classifier: Topic :: Scientific/Engineering :: Bio-Informatics
Requires-Python: >=3.6
Requires-Dist: dataclasses ; python_version == "3.6"
Provides-Extra: biosimulators
Requires-Dist: biosimulators-utils[logging] >=0.1.124 ; extra == 'biosimulators'
Requires-Dist: numpy ; extra == 'biosimulators'
Requires-Dist: pandas ; extra == 'biosimulators'
Requires-Dist: biosimulators-simularium >=0.5.29 ; extra == 'biosimulators'
Provides-Extra: biosimulators-dev
Requires-Dist: flake8 ; extra == 'biosimulators-dev'
Provides-Extra: biosimulators-tests
Requires-Dist: python-dateutil ; extra == 'biosimulators-tests'
Provides-Extra: dev
Requires-Dist: mypy ; extra == 'dev'
Requires-Dist: pyflakes ; extra == 'dev'
Requires-Dist: black ; extra == 'dev'
Requires-Dist: numpy ; extra == 'dev'
Requires-Dist: matplotlib ; extra == 'dev'
Requires-Dist: flaky ; extra == 'dev'
